mimikeepass/__init__.py
mimikeepass/cli.py
mimikeepass/client.py
mimikeepass/daemon.py
mimikeepass/environ.py
mimikeepass/py.typed
mimikeepass/socket.py
mimikeepass/askpass/__init__.py
mimikeepass/askpass/core.py
mimikeepass/askpass/ssh.py
mimikeepass-0.0.1.dist-info/LICENSE
mimikeepass-0.0.1.dist-info/METADATA
mimikeepass-0.0.1.dist-info/WHEEL
mimikeepass-0.0.1.dist-info/top_level.txt
mimikeepass-0.0.1.dist-info/RECORD
