Metadata-Version: 2.1
Name: mimikeepass
Version: 0.0.1
Summary: Read passwords for keepass database files
Author-email: Gabriel Corona <gabriel.corona@enst-bretagne.fr>
Classifier: Programming Language :: Python :: 3
Classifier: License :: OSI Approved :: MIT License
Classifier: Operating System :: OS Independent
Classifier: Topic :: Utilities
Requires-Python: >=3.8
License-File: LICENSE
Requires-Dist: pykeepass <5,>=4.0.6
Requires-Dist: click <9,>=8.1.6
